FunctionalPython/__init__.py
FunctionalPython/src/__init__.py
FunctionalPython/src/lists/__init__.py
FunctionalPython/src/lists/cart2.py
FunctionalPython/src/lists/cart_append.py
FunctionalPython/src/lists/cartn.py
FunctionalPython/src/lists/dict2list.py
FunctionalPython/src/lists/others.py
FunctionalPython/tests/__init__.py
FunctionalPython/tests/list/__init__.py
FunctionalPython/tests/list/cart2/__init__.py
FunctionalPython/tests/list/cart2/test_1.py
FunctionalPython-0.0.4.dist-info/DESCRIPTION.rst
FunctionalPython-0.0.4.dist-info/METADATA
FunctionalPython-0.0.4.dist-info/RECORD
FunctionalPython-0.0.4.dist-info/WHEEL
FunctionalPython-0.0.4.dist-info/metadata.json
FunctionalPython-0.0.4.dist-info/top_level.txt
