Metadata-Version: 2.0
Name: FunctionalPython
Version: 0.0.4
Summary: Functional programming in Python toolkit
Home-page: https://github.com/FunctionalX/FunctionalPython
Author: Yuhang(Steven) Wang
Author-email: stevenyhw.github@gmail.com
License: MIT
Keywords: functional programming
Platform: UNKNOWN
Classifier: Development Status :: 3 - Alpha
Classifier: Intended Audience :: Developers
Classifier: Topic :: Software Development :: Build Tools
Classifier: License :: OSI Approved :: MIT License
Classifier: Programming Language :: Python :: 3
Classifier: Programming Language :: Python :: 3.3
Classifier: Programming Language :: Python :: 3.4
Classifier: Programming Language :: Python :: 3.5
Provides-Extra: dev
Requires-Dist: check-manifest; extra == 'dev'
Provides-Extra: test
Requires-Dist: coverage; extra == 'test'
